event_plugin_system/__init__.py
event_plugin_system/base_plugin.py
event_plugin_system/event_plugin_system.py
event_plugin_system-0.0.8.dist-info/LICENSE
event_plugin_system-0.0.8.dist-info/METADATA
event_plugin_system-0.0.8.dist-info/WHEEL
event_plugin_system-0.0.8.dist-info/top_level.txt
event_plugin_system-0.0.8.dist-info/RECORD
