Metadata-Version: 2.1
Name: event-plugin-system
Version: 0.0.8
Summary: A simple plugin event system
Home-page: https://github.com/chalonga/event-plugin-system
Author: Carlos
Author-email: chalonga@gmail.com
Classifier: Programming Language :: Python :: 3
Classifier: License :: OSI Approved :: MIT License
Classifier: Operating System :: OS Independent
Requires-Python: >=3.6
License-File: LICENSE
